main.py
sen3r/__init__.py
sen3r/commons.py
sen3r/graphics.py
sen3r/nc_engine.py
sen3r/sen3r.py
sen3r/tsgen.py
sen3r-1.0.6.dist-info/LICENSE
sen3r-1.0.6.dist-info/METADATA
sen3r-1.0.6.dist-info/WHEEL
sen3r-1.0.6.dist-info/entry_points.txt
sen3r-1.0.6.dist-info/top_level.txt
sen3r-1.0.6.dist-info/RECORD
